odoo10_addon_l10n_es_aeat_vat_prorrate_asset-10.0.1.0.0-py2.7-nspkg.pth
odoo/addons/l10n_es_aeat_vat_prorrate_asset/README.rst
odoo/addons/l10n_es_aeat_vat_prorrate_asset/__init__.py
odoo/addons/l10n_es_aeat_vat_prorrate_asset/__manifest__.py
odoo/addons/l10n_es_aeat_vat_prorrate_asset/i18n/ca.po
odoo/addons/l10n_es_aeat_vat_prorrate_asset/i18n/cs.po
odoo/addons/l10n_es_aeat_vat_prorrate_asset/i18n/es.po
odoo/addons/l10n_es_aeat_vat_prorrate_asset/i18n/es_CO.po
odoo/addons/l10n_es_aeat_vat_prorrate_asset/i18n/es_CR.po
odoo/addons/l10n_es_aeat_vat_prorrate_asset/i18n/fr.po
odoo/addons/l10n_es_aeat_vat_prorrate_asset/i18n/gl.po
odoo/addons/l10n_es_aeat_vat_prorrate_asset/i18n/hr.po
odoo/addons/l10n_es_aeat_vat_prorrate_asset/i18n/nl.po
odoo/addons/l10n_es_aeat_vat_prorrate_asset/i18n/pl.po
odoo/addons/l10n_es_aeat_vat_prorrate_asset/i18n/pt.po
odoo/addons/l10n_es_aeat_vat_prorrate_asset/i18n/pt_BR.po
odoo/addons/l10n_es_aeat_vat_prorrate_asset/i18n/ru.po
odoo/addons/l10n_es_aeat_vat_prorrate_asset/i18n/sl.po
odoo/addons/l10n_es_aeat_vat_prorrate_asset/i18n/sv.po
odoo/addons/l10n_es_aeat_vat_prorrate_asset/i18n/tr.po
odoo/addons/l10n_es_aeat_vat_prorrate_asset/i18n/vi.po
odoo/addons/l10n_es_aeat_vat_prorrate_asset/models/__init__.py
odoo/addons/l10n_es_aeat_vat_prorrate_asset/models/account_asset_asset.py
odoo/addons/l10n_es_aeat_vat_prorrate_asset/models/account_invoice.py
odoo/addons/l10n_es_aeat_vat_prorrate_asset/models/mod303.py
odoo/addons/l10n_es_aeat_vat_prorrate_asset/static/description/icon.png
odoo/addons/l10n_es_aeat_vat_prorrate_asset/static/description/icon_source.svg
odoo/addons/l10n_es_aeat_vat_prorrate_asset/views/account_asset_asset_view.xml
odoo/addons/l10n_es_aeat_vat_prorrate_asset/views/account_invoice_view.xml
odoo10_addon_l10n_es_aeat_vat_prorrate_asset-10.0.1.0.0.dist-info/DESCRIPTION.rst
odoo10_addon_l10n_es_aeat_vat_prorrate_asset-10.0.1.0.0.dist-info/METADATA
odoo10_addon_l10n_es_aeat_vat_prorrate_asset-10.0.1.0.0.dist-info/RECORD
odoo10_addon_l10n_es_aeat_vat_prorrate_asset-10.0.1.0.0.dist-info/WHEEL
odoo10_addon_l10n_es_aeat_vat_prorrate_asset-10.0.1.0.0.dist-info/metadata.json
odoo10_addon_l10n_es_aeat_vat_prorrate_asset-10.0.1.0.0.dist-info/namespace_packages.txt
odoo10_addon_l10n_es_aeat_vat_prorrate_asset-10.0.1.0.0.dist-info/top_level.txt
